finishes_library/__init__.py
finishes_library/utils.py
finishes_library/finishes/__init__.py
finishes_library-0.1.0.dist-info/METADATA
finishes_library-0.1.0.dist-info/WHEEL
finishes_library-0.1.0.dist-info/top_level.txt
finishes_library-0.1.0.dist-info/RECORD
